odoo9_addon_website_sale_require_legal-9.0.1.1.0-py2.7-nspkg.pth
odoo9_addon_website_sale_require_legal-9.0.1.1.0.dist-info/DESCRIPTION.rst
odoo9_addon_website_sale_require_legal-9.0.1.1.0.dist-info/METADATA
odoo9_addon_website_sale_require_legal-9.0.1.1.0.dist-info/RECORD
odoo9_addon_website_sale_require_legal-9.0.1.1.0.dist-info/WHEEL
odoo9_addon_website_sale_require_legal-9.0.1.1.0.dist-info/metadata.json
odoo9_addon_website_sale_require_legal-9.0.1.1.0.dist-info/namespace_packages.txt
odoo9_addon_website_sale_require_legal-9.0.1.1.0.dist-info/top_level.txt
odoo_addons/website_sale_require_legal/README.rst
odoo_addons/website_sale_require_legal/__init__.py
odoo_addons/website_sale_require_legal/__openerp__.py
odoo_addons/website_sale_require_legal/controllers/__init__.py
odoo_addons/website_sale_require_legal/controllers/main.py
odoo_addons/website_sale_require_legal/i18n/de.po
odoo_addons/website_sale_require_legal/i18n/es.po
odoo_addons/website_sale_require_legal/i18n/hr.po
odoo_addons/website_sale_require_legal/i18n/it.po
odoo_addons/website_sale_require_legal/i18n/sl.po
odoo_addons/website_sale_require_legal/static/description/icon.png
odoo_addons/website_sale_require_legal/views/website_sale.xml
