Metadata-Version: 2.0
Name: odoo9-addon-website-sale-require-legal
Version: 9.0.1.1.0
Summary: Force the user to accept legal tems to buy in the web shop
Home-page: http://github.com/OCA/e-commerce
Author: Antiun Ingeniería S.L., Tecnativa, Odoo Community Association (OCA)
Author-email: support@odoo-community.org
License: AGPL-3
Platform: UNKNOWN
Classifier: Programming Language :: Python
Classifier: Framework :: Odoo
Classifier: License :: OSI Approved :: GNU Affero General Public License v3
Requires-Python: ~=2.7
Requires-Dist: odoo (<9.1a,>=9.0a)
Requires-Dist: odoo9-addon-website-legal-page
